psg.py
psg-0.0.2.dist-info/METADATA
psg-0.0.2.dist-info/WHEEL
psg-0.0.2.dist-info/top_level.txt
psg-0.0.2.dist-info/RECORD
