Metadata-Version: 2.1
Name: psg
Version: 0.0.2
Summary: Pakistan SUI Gas Bills and Tariff
Home-page: https://www.techtum.dev/work-psg-220228.html#work-psg-220228
Author: siphr
Author-email: pypi@techtum.dev
License: UNKNOWN
Project-URL: Bug Tracker, https://github.com/siphr/psg/issues
Platform: UNKNOWN
Classifier: Programming Language :: Python :: 3
Classifier: License :: OSI Approved :: MIT License
Classifier: Operating System :: OS Independent
Requires-Python: >=3.6
